Workbook

Sheet - AYUDA -
B4: Ayuda

Sheet Precios 
B5: Comparación de Precios entre diferentes proveedores
B6: Ingresa en la tabla los productos, los proveedores y sus precios
J7: ESTADÍSTICAS POR PRODUCTO
B8: PRODUCTO | C8: CANTIDAD | D8: PROVEEDOR 1 (ALKOSTO) | E8: PROVEEDOR 2 | F8: PROVEEDOR 3 | G8: PROVEEDOR 4 | H8: PROVEEDOR 5 | I8: PROVEEDOR 6 | J8: PRECIO MÁS BAJO | K8: PRECIO PROMEDIO | L8: PRECIO MÁS ALTO
B9: Lavadora LG carga superior 16 kg WT16MVTB | C9: 1 | D9: 1599050 | E9: 1630000 | F9: 1590000 | J9: 1590000 | K9: 1606350 | L9: 1630000
B10: mart TV Samsung 75″ Crystal UHD U8000 | C10: 1 | D10: 3199030 | E10: 3250000 | F10: 3300000 | J10: 3199030 | K10: 3249677 | L10: 3300000
B11: Portátil ASUS Vivobook 16″ Ryzen 5, 16 GB RAM, 512 GB SSD | C11: 1 | D11: 2399030 | E11: 2450000 | F11: $2,380,000 | J11: 2380000 | K11: 2409677 | L11: 2450000
B12: Nevera Haceb No Frost 294 L con dispensado | C12: 1 | D12: $ 1,779,050 | E12: 1810000 | F12: 1790000 | J12: =MIN('Precios '!$D12:$I12) -> 1790000 | K12: =IFERROR(AVERAGE('Precios '!$D12:$I12),0) -> 1800000 | L12: =MAX('Precios '!$D12:$I12) -> 1810000
B13: Freidora de aire Imusa Max 5 L digital | C13: 1 | D13: 299900 | E13: 315000 | F13: 305000 | J13: 299900 | K13: 306633 | L13: $ 315,000
B14: Olla a presión IMUSA 7 L Talent Master | C14: 1 | D14: 399900 | E14: $ 410,000 | F14: $ 385,000 | J14: $385,000 | K14: 398300 | L14: $ 410,000
B15: Juego de ollas IMUSA Hard Titanium | C15: 1 | D15: $ 331,200 | E15: $ 340,000 | F15: $345,000 | J15: 331200 | K15: $338,733 | L15: $ 345,000
B16: Licuadora Oster Reversible 600 W vidrio | C16: 1 | D16: 259900 | E16: 269900 | F16: 275000 | J16: $ 259,900 | K16: $ 268,266 | L16: $ 275,000
B17: PlayStation 5 Slim (con disco) | C17: 1 | D17: 2639900 | E17: 2700000 | F17: 2650000 | J17: 2639900 | K17: =IFERROR(AVERAGE('Precios '!$D17:$I17),0) -> 2663300 | L17: =MAX('Precios '!$D17:$I17) -> 2700000
B18: Altavoz Bluetooth JBL Xtreme 4 | C18: 1 | D18: $ 376,195 | E18: $ 389,000 | F18: 380000 | J18: 376195 | K18: 5 $381,731 | L18: $389,000
K19: =IFERROR(AVERAGE('Precios '!$D19:$I19),0) -> 0 | L19: =MAX('Precios '!$D19:$I19) -> 0
J20: =MIN('Precios '!$D20:$I20) -> 0 | K20: =IFERROR(AVERAGE('Precios '!$D20:$I20),0) -> 0 | L20: =MAX('Precios '!$D20:$I20) -> 0
J21: =MIN('Precios '!$D21:$I21) -> 0 | K21: =IFERROR(AVERAGE('Precios '!$D21:$I21),0) -> 0 | L21: =MAX('Precios '!$D21:$I21) -> 0
J22: =MIN('Precios '!$D22:$I22) -> 0 | K22: =IFERROR(AVERAGE('Precios '!$D22:$I22),0) -> 0 | L22: =MAX('Precios '!$D22:$I22) -> 0
J23: =MIN('Precios '!$D23:$I23) -> 0 | K23: =IFERROR(AVERAGE('Precios '!$D23:$I23),0) -> 0 | L23: =MAX('Precios '!$D23:$I23) -> 0
J24: =MIN('Precios '!$D24:$I24) -> 0 | K24: =IFERROR(AVERAGE('Precios '!$D24:$I24),0) -> 0 | L24: =MAX('Precios '!$D24:$I24) -> 0
J25: =MIN('Precios '!$D25:$I25) -> 0 | K25: =IFERROR(AVERAGE('Precios '!$D25:$I25),0) -> 0 | L25: =MAX('Precios '!$D25:$I25) -> 0
B26: Total | D26: =ROUND(SUMPRODUCT('Precios '!$C$9:$C$25,'Precios '!$D$9:$D$25),2) -> 10796710 | E26: =ROUND(SUMPRODUCT('Precios '!$C$9:$C$25,'Precios '!$E$9:$E$25),2) -> 12424900 | F26: =ROUND(SUMPRODUCT('Precios '!$C$9:$C$25,'Precios '!$F$9:$F$25),2) -> 10290000 | G26: =ROUND(SUMPRODUCT('Precios '!$C$9:$C$25,'Precios '!$G$9:$G$25),2) -> 0 | H26: =ROUND(SUMPRODUCT('Precios '!$C$9:$C$25,'Precios '!$H$9:$H$25),2) -> 0 | I26: =ROUND(SUMPRODUCT('Precios '!$C$9:$C$25,'Precios '!$I$9:$I$25),2) -> 0
B29: DATOS ADICIONALES
B30: TIEMPO DE ENTREGA (DIAS) | D30: HORAS DEL DIA LOS 7 DIAS DE LA SEMANA | E30: de 3 a 5 minutos | F30: 3 a 10 dias habiles | G30: entrega de 2 dias habiles | H30: 1 a 5 dias habiles | I30: 5 dias laborales
B31: COSTO DE ENVÍO | D31: 0 | E31: 7.055 | F31: $287.497 | G31: 0 | H31: $295.39 | I31: 0
B32: FORMAS DE PAGO | E32: Productos digitales, como PIN o licencias | F32: Productos grandes como neveras o lavadora | G32: Productos pequeños o disponibles en tienda | H32: Tecnología y hogar | I32: Envío nacional estándar
D34: CONTADO | E34: CONTADO / PAGO EN LINEA | F34: CONTADO / TARJETA DE CREDITO / PSE | G34: CONTADO | H34: CONTADO O CREDITO ALKOSTO | I34: CONTADO / PSE / CRÉDITO ALKOSTO

Sheet Precios  (2)
B5: Comparación de Precios entre diferentes proveedores
B6: Ingresa en la tabla los productos, los proveedores y sus precios
J7: ESTADÍSTICAS POR PRODUCTO
B8: PRODUCTO | C8: CANTIDAD | D8: PROVEEDOR 1 | E8: PROVEEDOR 2 | F8: PROVEEDOR 3 | G8: PROVEEDOR 4 | H8: PROVEEDOR 5 | I8: PROVEEDOR 6 | J8: PRECIO MÁS BAJO | K8: PRECIO PROMEDIO | L8: PRECIO MÁS ALTO
B9: iPhone 13 128 GB Azul | C9: 3 | D9: $2.199.010 | E9: $2.250.000 | F9: $2.180.000 | G9: $2.220.000 | H9: $2.300.000 | I9: $2.210.000 | J9: $2.180.000 | K9: $2.226.667 | L9: $2.300.000
B10: TV Samsung 75" U8000F 4K | C10: 3 | D10: $5.899.900 | E10: $5.850.000 | F10: $5.920.000 | G10: $5.880.000 | H10: $5.910.000 | I10: $5.940.000 | J10: $5.850.000 | K10: $5.900.000 | L10: $5.940.000
B11: Laptop HP 15" i5 / 8 GB / SSD 512 GB | C11: 3 | D11: $1.849.030 | E11: $1.830.000 | F11: $1.870.000 | G11: $1.840.000 | H11: $1.860.000 | I11: $1.855.000 | J11: $1.830.000 | K11: $1.857.005 | L11: $1.870.000
B12: Lavadora LG 16 kg carga superior | C12: 3 | D12: $1.439.050 | E12: $1.420.000 | F12: $1.450.000 | G12: $1.435.000 | H12: $1.445.000 | I12: $1.440.000 | J12: $1.420.000 | K12: $1.438.333 | L12: $1.450.000
B13: Olla a presión Kalley 6 L | C13: 3 | D13: 195.8 | E13: 190 | F13: 200 | G13: 193 | H13: 198 | I13: 197 | J13: 190 | K13: 195.8 | L13: 200
B14: Freidora de aire Imusa Max 5 L | C14: 3 | D14: 479.9 | E14: 470 | F14: 485 | G14: 475 | H14: 480 | I14: 482 | J14: 470 | K14: 479.8 | L14: 485
B15: Llanta Goodyear 185/65R14 | C15: 3 | D15: 406.9 | E15: 400 | F15: 410 | G15: 405 | H15: 408 | I15: 407 | J15: 400 | K15: 406.65 | L15: 410
B16: Nevera LG No Frost 374 L | C16: 3 | D16: $4.499.900 | E16: $4.480.000 | F16: $4.520.000 | G16: $4.490.000 | H16: $4.510.000 | I16: $4.505.000 | J16: $4.480.000 | K16: $4.500.800 | L16: $4.520.000
B17: Nevecón LG InstaView 635 L | C17: 3 | D17: $14.799.900 | E17: $14.750.000 | F17: $14.820.000 | G17: $14.780.000 | H17: $14.810.000 | I17: $14.805.000 | J17: $14.750.000 | K17: $14.790.800 | L17: $14.820.000
B18: Nevera Haceb No Frost 294 L | C18: 3 | D18: $1.659.050 | E18: $1.640.000 | F18: $1.670.000 | G18: $1.655.000 | H18: $1.665.000 | I18: $1.660.000 | J18: $1.640.000 | K18: $1.658.333 | L18: $1.670.000
B19: Nevecón Samsung Side by Side 583 L | C19: 3 | D19: $3.749.050 | E19: $3.730.000 | F19: $3.760.000 | G19: $3.745.000 | H19: $3.755.000 | I19: $3.750.000 | J19: $3.730.000 | K19: $3.749.167 | L19: $3.760.000
B20: Nevera Mabe No Frost 394 L | C20: 3 | D20: $2.819.900 | E20: $2.800.000 | F20: $2.840.000 | G20: $2.815.000 | H20: $2.830.000 | I20: $2.825.000 | J20: $2.800.000 | K20: $2.823.483 | L20: $2.840.000
B21: Nevecón Whirlpool Xpert 518 L | C21: 3 | D21: $5.829.900 | E21: $5.800.000 | F21: $5.860.000 | G21: $5.825.000 | H21: $5.845.000 | I21: 5.830.000 | J21: $5.800.000 | K21: $5.828.650 | L21: $5.860.000
J22: =MIN('Precios (2)'!$D22:$I22) -> 0 | K22: =IFERROR(AVERAGE('Precios (2)'!$D22:$I22),0) -> 0 | L22: =MAX('Precios (2)'!$D22:$I22) -> 0
J23: =MIN('Precios (2)'!$D23:$I23) -> 0 | K23: =IFERROR(AVERAGE('Precios (2)'!$D23:$I23),0) -> 0 | L23: =MAX('Precios (2)'!$D23:$I23) -> 0
J24: =MIN('Precios (2)'!$D24:$I24) -> 0 | K24: =IFERROR(AVERAGE('Precios (2)'!$D24:$I24),0) -> 0 | L24: =MAX('Precios (2)'!$D24:$I24) -> 0
B25: Total | D25: =ROUND(SUMPRODUCT('Precios (2)'!$C$9:$C$24,'Precios (2)'!$D$9:$D$24),2) -> 3247.8 | E25: =ROUND(SUMPRODUCT('Precios (2)'!$C$9:$C$24,'Precios (2)'!$E$9:$E$24),2) -> 3180 | F25: =ROUND(SUMPRODUCT('Precios (2)'!$C$9:$C$24,'Precios (2)'!$F$9:$F$24),2) -> 3285 | G25: =ROUND(SUMPRODUCT('Precios (2)'!$C$9:$C$24,'Precios (2)'!$G$9:$G$24),2) -> 3219 | H25: =ROUND(SUMPRODUCT('Precios (2)'!$C$9:$C$24,'Precios (2)'!$H$9:$H$24),2) -> 3258 | I25: =ROUND(SUMPRODUCT('Precios (2)'!$C$9:$C$24,'Precios (2)'!$I$9:$I$24),2) -> 17493258
B28: DATOS ADICIONALES
B29: TIEMPO DE ENTREGA (DÍAS) | D29: Proveedor 1: 5-7 días | E29: Proveedor 2: 3-5 días ⭐ | F29: Proveedor 3: 7-10 días | G29: Proveedor 4: 4-6 días | H29: Proveedor 5: 5-8 días | I29: Proveedor 6: 6-8 días
B30: COSTO DE ENVÍO | D30: 50 | E30: $35.000 ⭐ | F30: 45 | G30: 40 | H30: 55 | I30: 48
B31: FORMAS DE PAGO
D32: Transferencia, Efectivo, Tarjeta de crédito | E32: Transferencia, Efectivo ⭐ | G32: Transferencia, Efectivo, Tarjeta | H32: Transferencia, Crédito 15 días | I32: Transferencia, Efectivo, Crédito 30 días

Sheet Soporte
B7: Almendras | C7: 1 | D7: 498 | E7: 420 | F7: 450 | G7: 230 | H7: 600 | I7: 520
B8: Nueces | C8: 2 | D8: 450 | E8: 220 | F8: 405 | G8: 495 | H8: 540 | I8: 200
B9: Pistachos | C9: 2 | D9: 650 | E9: 620 | F9: 666 | G9: 400 | H9: 648 | I9: 452.4
B10: Pecán | C10: 1 | D10: 585 | E10: 558 | F10: 320 | G10: 360 | H10: 583.2 | I10: 407.16
B11: Bananas | C11: 3 | D11: 526.5 | E11: 502.2 | F11: 539.46 | G11: 300 | H11: 500 | I11: 366.44
B12: Pasas | C12: 1 | D12: 473.8 | E12: 200 | F12: 485.51 | G12: 291.6 | H12: 270 | I12: 220
D19: 30 | E19: 10 | F19: 15 | G19: 15 | H19: 15 | I19: 10
D20: 10 | E20: 10 | F20: 10 | G20: Gratis | H20: 5 | I20: Gratis
D21: Efvo | E21: Efvo | F21: Mercado Pago | G21: Efectivo | H21: Mercado Pago | I21: Mercado Pago
D22: Tarjeta | E22: Tarjeta | F22: Tarjeta cuotas | G22: Mercado Pago | H22: Tarjeta cuotas | I22: Tarjeta cuotas
B28: Piñones | C28: 1 | D28: 340 | E28: 330 | F28: 440 | G28: 400 | H28: 320 | I28: 330
B29: Cranberries | C29: 1 | D29: 220 | E29: 230 | F29: 240 | G29: 220 | H29: 219 | I29: 218
B30: Castañas | C30: 2 | D30: 560 | E30: 580 | F30: 550 | G30: 520 | H30: 551 | I30: 550
B35: China Co
B36: 250
B37: 440
B38: 440
B39: 350
B40: 420
B41: 199
